qgis_server_light/interface/__init__.py
qgis_server_light/interface/dispatcher.py
qgis_server_light/interface/job.py
qgis_server_light/interface/qgis.py
qgis_server_light-0.0.2.dist-info/LICENSE
qgis_server_light-0.0.2.dist-info/METADATA
qgis_server_light-0.0.2.dist-info/WHEEL
qgis_server_light-0.0.2.dist-info/top_level.txt
qgis_server_light-0.0.2.dist-info/RECORD
